access/cnes_grace_sync.py
access/esa_costg_swarm_sync.py
access/gfz_icgem_costg_ftp.py
access/gfz_isdc_dealiasing_sync.py
access/gfz_isdc_grace_sync.py
access/itsg_graz_grace_sync.py
access/podaac_cumulus.py
dealiasing/aod1b_geocenter.py
dealiasing/aod1b_oblateness.py
dealiasing/dealiasing_global_uplift.py
dealiasing/dealiasing_monthly_mean.py
geocenter/calc_degree_one.py
geocenter/geocenter_compare_tellus.py
geocenter/geocenter_monte_carlo.py
geocenter/geocenter_ocean_models.py
geocenter/geocenter_processing_centers.py
geocenter/monte_carlo_degree_one.py
gravity_toolkit/__init__.py
gravity_toolkit/associated_legendre.py
gravity_toolkit/clenshaw_summation.py
gravity_toolkit/degree_amplitude.py
gravity_toolkit/destripe_harmonics.py
gravity_toolkit/fourier_legendre.py
gravity_toolkit/gauss_weights.py
gravity_toolkit/gen_averaging_kernel.py
gravity_toolkit/gen_disc_load.py
gravity_toolkit/gen_harmonics.py
gravity_toolkit/gen_point_load.py
gravity_toolkit/gen_spherical_cap.py
gravity_toolkit/gen_stokes.py
gravity_toolkit/geocenter.py
gravity_toolkit/grace_date.py
gravity_toolkit/grace_find_months.py
gravity_toolkit/grace_input_months.py
gravity_toolkit/grace_months_index.py
gravity_toolkit/harmonic_gradients.py
gravity_toolkit/harmonic_summation.py
gravity_toolkit/harmonics.py
gravity_toolkit/legendre.py
gravity_toolkit/legendre_polynomials.py
gravity_toolkit/mascons.py
gravity_toolkit/ocean_stokes.py
gravity_toolkit/read_GIA_model.py
gravity_toolkit/read_GRACE_harmonics.py
gravity_toolkit/read_SLR_harmonics.py
gravity_toolkit/read_gfc_harmonics.py
gravity_toolkit/read_love_numbers.py
gravity_toolkit/sea_level_equation.py
gravity_toolkit/spatial.py
gravity_toolkit/time.py
gravity_toolkit/tools.py
gravity_toolkit/units.py
gravity_toolkit/utilities.py
gravity_toolkit/version.py
gravity_toolkit/SLR/C20.py
gravity_toolkit/SLR/C30.py
gravity_toolkit/SLR/C40.py
gravity_toolkit/SLR/C50.py
gravity_toolkit/SLR/CS2.py
gravity_toolkit/SLR/__init__.py
gravity_toolkit-1.2.5.dist-info/licenses/LICENSE
gravity_toolkit-1.2.5.dist-info/METADATA
gravity_toolkit-1.2.5.dist-info/WHEEL
gravity_toolkit-1.2.5.dist-info/top_level.txt
gravity_toolkit-1.2.5.dist-info/RECORD
