Metadata-Version: 2.4
Name: gravity-toolkit
Version: 1.2.5
Summary: Python tools for working with time-variable gravity fields
Author: Tyler Sutterley, Hugo Lecomte, Yara Mohajerani, Isabella Velicogna
Author-email: tsutterl@uw.edu
Maintainer: gravity-toolkit contributors
License: MIT License
Project-URL: Homepage, https://gravity-toolkit.readthedocs.io
Project-URL: Documentation, https://gravity-toolkit.readthedocs.io
Project-URL: Repository, https://github.com/tsutterley/gravity-toolkit
Project-URL: Issues, https://github.com/tsutterley/gravity-toolkit/issues
Keywords: GRACE,GRACE-FO,Gravity,satellite geodesy,spherical harmonics
Classifier: Development Status :: 3 - Alpha
Classifier: Intended Audience :: Science/Research
Classifier: License :: OSI Approved :: MIT License
Classifier: Operating System :: OS Independent
Classifier: Programming Language :: Python :: 3
Classifier: Programming Language :: Python :: 3.6
Classifier: Programming Language :: Python :: 3.7
Classifier: Programming Language :: Python :: 3.8
Classifier: Programming Language :: Python :: 3.9
Classifier: Programming Language :: Python :: 3.10
Classifier: Programming Language :: Python :: 3.11
Classifier: Programming Language :: Python :: 3.12
Classifier: Topic :: Scientific/Engineering :: Physics
Requires-Python: ~=3.6
License-File: LICENSE
Requires-Dist: boto3
Requires-Dist: future
Requires-Dist: lxml
Requires-Dist: matplotlib
Requires-Dist: netCDF4
Requires-Dist: numpy
Requires-Dist: python-dateutil
Requires-Dist: pyyaml
Requires-Dist: scipy>=1.10.1
Provides-Extra: doc
Requires-Dist: docutils; extra == "doc"
Requires-Dist: graphviz; extra == "doc"
Requires-Dist: myst-nb; extra == "doc"
Requires-Dist: numpydoc; extra == "doc"
Requires-Dist: sphinx; extra == "doc"
Requires-Dist: sphinx-argparse>=0.4; extra == "doc"
Requires-Dist: sphinxcontrib-bibtex; extra == "doc"
Requires-Dist: sphinx-design; extra == "doc"
Requires-Dist: sphinx_rtd_theme; extra == "doc"
Provides-Extra: all
Requires-Dist: cartopy; extra == "all"
Requires-Dist: geoid-toolkit; extra == "all"
Requires-Dist: h5py; extra == "all"
Requires-Dist: jupyterlab; extra == "all"
Requires-Dist: jupyterlab_widgets; extra == "all"
Requires-Dist: notebook; extra == "all"
Requires-Dist: shapely; extra == "all"
Provides-Extra: dev
Requires-Dist: flake8; extra == "dev"
Requires-Dist: pytest>=4.6; extra == "dev"
Requires-Dist: pytest-cov; extra == "dev"
Requires-Dist: pytest-xdist; extra == "dev"
Dynamic: license-file
